<annotation>
	<folder>images</folder>
	<filename>grapefruit (5).jpg</filename>
	<path>/home/alexmarin/Desktop/LICENTA/dataset_creation/processing_fruits/grapefruits/images/grapefruit (5).jpg</path>
	<source>
		<database>Unknown</database>
	</source>
	<size>
		<width>400</width>
		<height>400</height>
		<depth>3</depth>
	</size>
	<segmented>0</segmented>
	<object>
		<name>grapefruit</name>
		<pose>Unspecified</pose>
		<truncated>0</truncated>
		<difficult>0</difficult>
		<bndbox>
			<xmin>14</xmin>
			<ymin>35</ymin>
			<xmax>231</xmax>
			<ymax>250</ymax>
		</bndbox>
	</object>
	<object>
		<name>grapefruit</name>
		<pose>Unspecified</pose>
		<truncated>0</truncated>
		<difficult>0</difficult>
		<bndbox>
			<xmin>167</xmin>
			<ymin>159</ymin>
			<xmax>379</xmax>
			<ymax>357</ymax>
		</bndbox>
	</object>
</annotation>
