<annotation>
	<folder>images</folder>
	<filename>pear (10).jpg</filename>
	<path>/home/alexmarin/Desktop/LICENTA/dataset_creation/processing_fruits/pears/images/pear (10).jpg</path>
	<source>
		<database>Unknown</database>
	</source>
	<size>
		<width>493</width>
		<height>335</height>
		<depth>3</depth>
	</size>
	<segmented>0</segmented>
	<object>
		<name>pear</name>
		<pose>Unspecified</pose>
		<truncated>0</truncated>
		<difficult>0</difficult>
		<bndbox>
			<xmin>81</xmin>
			<ymin>13</ymin>
			<xmax>209</xmax>
			<ymax>278</ymax>
		</bndbox>
	</object>
	<object>
		<name>pear</name>
		<pose>Unspecified</pose>
		<truncated>0</truncated>
		<difficult>0</difficult>
		<bndbox>
			<xmin>21</xmin>
			<ymin>92</ymin>
			<xmax>94</xmax>
			<ymax>243</ymax>
		</bndbox>
	</object>
	<object>
		<name>pear</name>
		<pose>Unspecified</pose>
		<truncated>0</truncated>
		<difficult>0</difficult>
		<bndbox>
			<xmin>198</xmin>
			<ymin>159</ymin>
			<xmax>399</xmax>
			<ymax>312</ymax>
		</bndbox>
	</object>
	<object>
		<name>pear</name>
		<pose>Unspecified</pose>
		<truncated>0</truncated>
		<difficult>0</difficult>
		<bndbox>
			<xmin>233</xmin>
			<ymin>116</ymin>
			<xmax>394</xmax>
			<ymax>173</ymax>
		</bndbox>
	</object>
	<object>
		<name>pear</name>
		<pose>Unspecified</pose>
		<truncated>0</truncated>
		<difficult>0</difficult>
		<bndbox>
			<xmin>395</xmin>
			<ymin>148</ymin>
			<xmax>473</xmax>
			<ymax>298</ymax>
		</bndbox>
	</object>
</annotation>
