<annotation>
	<folder>images</folder>
	<filename>strawberry (12).jpg</filename>
	<path>/home/alexmarin/Desktop/LICENTA/dataset_creation/processing_fruits/strawberries/images/strawberry (12).jpg</path>
	<source>
		<database>Unknown</database>
	</source>
	<size>
		<width>1310</width>
		<height>755</height>
		<depth>3</depth>
	</size>
	<segmented>0</segmented>
	<object>
		<name>strawberry</name>
		<pose>Unspecified</pose>
		<truncated>0</truncated>
		<difficult>0</difficult>
		<bndbox>
			<xmin>90</xmin>
			<ymin>275</ymin>
			<xmax>383</xmax>
			<ymax>586</ymax>
		</bndbox>
	</object>
	<object>
		<name>strawberry</name>
		<pose>Unspecified</pose>
		<truncated>0</truncated>
		<difficult>0</difficult>
		<bndbox>
			<xmin>418</xmin>
			<ymin>294</ymin>
			<xmax>758</xmax>
			<ymax>637</ymax>
		</bndbox>
	</object>
	<object>
		<name>strawberry</name>
		<pose>Unspecified</pose>
		<truncated>0</truncated>
		<difficult>0</difficult>
		<bndbox>
			<xmin>345</xmin>
			<ymin>135</ymin>
			<xmax>644</xmax>
			<ymax>340</ymax>
		</bndbox>
	</object>
	<object>
		<name>strawberry</name>
		<pose>Unspecified</pose>
		<truncated>0</truncated>
		<difficult>0</difficult>
		<bndbox>
			<xmin>736</xmin>
			<ymin>142</ymin>
			<xmax>1072</xmax>
			<ymax>453</ymax>
		</bndbox>
	</object>
</annotation>
